hello/__init__.py
hello/ext.cpython-37m-darwin.so
hello_chmike-0.0.0.dist-info/LICENSE.txt
hello_chmike-0.0.0.dist-info/METADATA
hello_chmike-0.0.0.dist-info/WHEEL
hello_chmike-0.0.0.dist-info/top_level.txt
hello_chmike-0.0.0.dist-info/RECORD
