Metadata-Version: 2.1
Name: hello_chmike
Version: 0.0.0
Summary: Simple python module with external C library
Home-page: https://github.com/chmike/hello
Maintainer: Christophe Meessen
Maintainer-email: christophe@meessen.net
License: BSD 3-Clause License
Keywords: Example
Platform: UNKNOWN
Classifier: License :: OSI Approved :: BSD License
Classifier: Programming Language :: Python :: 3
Classifier: Operating System :: OS Independent
Classifier: Topic :: Utilities
Requires-Python: >=3.6
